pdenetgen/__init__.py
pdenetgen/model/__init__.py
pdenetgen/model/model.py
pdenetgen/model/nn_model.py
pdenetgen/symbolic/__init__.py
pdenetgen/symbolic/constants.py
pdenetgen/symbolic/dynamics.py
pdenetgen/symbolic/finite_difference.py
pdenetgen/symbolic/model_builder.py
pdenetgen/symbolic/model_builder_NN.py
pdenetgen/symbolic/nn_builder.py
pdenetgen/symbolic/tool.py
pdenetgen/symbolic/util.py
pdenetgen/symbolic/templates/__init__.py
pdenetgen/symbolic/templates/body_NNModelBuilder.py
pdenetgen/symbolic/templates/footer_NNModelBuilder.py
pdenetgen/symbolic/templates/header_NNModelBuilder.py
pdenetgen/symbolic/templates/licence.py
pdenetgen/symbolic/test/__init__.py
pdenetgen/symbolic/test/ref_burgers_NN_code.py
pdenetgen/symbolic/test/test_Eq.py
pdenetgen/symbolic/test/test_code.py
pdenetgen/symbolic/test/test_consistancy.py
pdenetgen/symbolic/test/test_coordinate.py
pdenetgen/symbolic/test/test_generate-trainable-burgers.py
pdenetgen-1.0.2.dist-info/LICENCE.txt
pdenetgen-1.0.2.dist-info/METADATA
pdenetgen-1.0.2.dist-info/WHEEL
pdenetgen-1.0.2.dist-info/top_level.txt
pdenetgen-1.0.2.dist-info/RECORD
