Metadata-Version: 2.1
Name: pdenetgen
Version: 1.0.2
Summary: Partial Differential Equation Network Generator
Home-page: https://github.com/opannekoucke/pdenetgen
Author: Olivier Pannekoucke 
Author-email: olivier.pannekoucke@meteo.fr
License: UNKNOWN
Project-URL: Bug Tracker, https://github.com/opannekoucke/pdenetgen/issues
Platform: UNKNOWN
Classifier: Programming Language :: Python :: 3
Classifier: License :: CeCILL-B Free Software License Agreement (CECILL-B) 
Classifier: Operating System :: OS Independent
Requires-Python: >=3.6
License-File: LICENCE.txt
